gocept.testing-4.0-py3.11-nspkg.pth
gocept/testing/__init__.py
gocept/testing/assertion.py
gocept/testing/fixture.py
gocept/testing/mock.py
gocept/testing/mtime.py
gocept/testing/patch.py
gocept/testing/tests/test_assertion.py
gocept/testing/tests/test_fixture.py
gocept/testing/tests/test_mock.py
gocept/testing/tests/test_mtime.py
gocept/testing/tests/test_patch.py
gocept.testing-4.0.dist-info/LICENSE.txt
gocept.testing-4.0.dist-info/METADATA
gocept.testing-4.0.dist-info/WHEEL
gocept.testing-4.0.dist-info/namespace_packages.txt
gocept.testing-4.0.dist-info/top_level.txt
gocept.testing-4.0.dist-info/RECORD
